.DS_Store
pyoutlet/__init__.py
pyoutlet/__main__.py
pyoutlet/codes_outlets.json
pyoutlet/switch.sh
pyoutlet-0.0.8.dist-info/DESCRIPTION.rst
pyoutlet-0.0.8.dist-info/LICENSE.txt
pyoutlet-0.0.8.dist-info/METADATA
pyoutlet-0.0.8.dist-info/RECORD
pyoutlet-0.0.8.dist-info/WHEEL
pyoutlet-0.0.8.dist-info/entry_points.txt
pyoutlet-0.0.8.dist-info/metadata.json
pyoutlet-0.0.8.dist-info/top_level.txt
pyoutletweb/__init__.py
pyoutletweb/__main__.py
pyoutletweb/views.py
pyoutletweb/static/css/bootstrap-flex.min.css
pyoutletweb/static/css/bootstrap-flex.min.css.map
pyoutletweb/templates/layout.html
pyoutletweb/templates/macros.html
pyoutletweb/templates/outlets_control.html
pyoutletweb/templates/outlets_editor.html
