Metadata-Version: 2.0
Name: pyoutlet
Version: 0.0.8
Summary: Python CLI & Web switcher for Etekcity power outlets using 433MHz RF emitter
Home-page: https://github.com/azogue/pyoutlet
Author: Eugenio Panadero
Author-email: azogue.lab@gmail.com
License: MIT
Keywords: home-automation power outlet raspberry
Platform: UNKNOWN
Classifier: Development Status :: 3 - Alpha
Classifier: Environment :: Console
Classifier: Intended Audience :: Developers
Classifier: Intended Audience :: Education
Classifier: Intended Audience :: Information Technology
Classifier: Topic :: Home Automation
Classifier: License :: OSI Approved :: MIT License
Classifier: Programming Language :: Python :: 3.5
Classifier: Operating System :: Unix
Requires-Dist: flask (>=0.11)
Requires-Dist: jsondiff (>=1.0.0)
